pychess/__init__.py
pychess/__main__.py
pychess/game.py
terminal_chess-0.0.2.dist-info/LICENSE
terminal_chess-0.0.2.dist-info/METADATA
terminal_chess-0.0.2.dist-info/WHEEL
terminal_chess-0.0.2.dist-info/entry_points.txt
terminal_chess-0.0.2.dist-info/top_level.txt
terminal_chess-0.0.2.dist-info/RECORD
