Metadata-Version: 2.1
Name: terminal-chess
Version: 0.0.2
Summary: A minimalistic python terminal-chess application
Author-email: Kevin Tarta <kevtar@gmail.com>
Maintainer-email: Kevin Tarta <kevtar@gmail.com>
License: MIT License
Project-URL: Source, https://github.com/elveskevtar/terminal-chess
Project-URL: Tracker, https://github.com/elveskevtar/terminal-chess/issues
Project-URL: Changelog, https://github.com/elveskevtar/terminal-chess/blob/mainline/CHANGELOG.md
Keywords: chess,terminal,console,interactive
Classifier: Development Status :: 3 - Alpha
Classifier: Environment :: Console
Classifier: License :: OSI Approved :: MIT License
Classifier: Programming Language :: Python
Classifier: Programming Language :: Python :: 3
Classifier: Topic :: Games/Entertainment
Classifier: Topic :: Games/Entertainment :: Board Games
Classifier: Topic :: Games/Entertainment :: Turn Based Strategy
Requires-Python: >=3.8
License-File: LICENSE
Provides-Extra: dev
Requires-Dist: pytest (==7.1.2) ; extra == 'dev'
Requires-Dist: flake8 (==4.0.1) ; extra == 'dev'
Requires-Dist: build (==0.10.0) ; extra == 'dev'
Requires-Dist: twine (==4.0.2) ; extra == 'dev'
